LICENSE
MANIFEST.in
README.md
VERSION
requirements.txt
requirements_dev.txt
setup.cfg
setup.py
wav2mel/__init__.py
wav2mel/__main__.py
wav2mel/audio.py
wav2mel/griffin_lim.py
wav2mel/py.typed
wav2mel/utils.py
wav2mel.egg-info/PKG-INFO
wav2mel.egg-info/SOURCES.txt
wav2mel.egg-info/dependency_links.txt
wav2mel.egg-info/entry_points.txt
wav2mel.egg-info/requires.txt
wav2mel.egg-info/top_level.txt