Metadata-Version: 2.1
Name: wav2mel
Version: 0.3.0
Summary: Convert WAV files to Mel spectrograms
Home-page: https://github.com/synesthesiam/wav2mel
Author: Michael Hansen
Author-email: mike@rhasspy.org
License: UNKNOWN
Platform: UNKNOWN
Classifier: Programming Language :: Python :: 3
Classifier: Programming Language :: Python :: 3.6
Classifier: Programming Language :: Python :: 3.7
Classifier: Programming Language :: Python :: 3.8
Classifier: License :: OSI Approved :: MIT License
Requires-Python: >=3.6
